gadfastsentry/__init__.py
gadfastsentry-0.0.1.dist-info/LICENSE
gadfastsentry-0.0.1.dist-info/METADATA
gadfastsentry-0.0.1.dist-info/WHEEL
gadfastsentry-0.0.1.dist-info/top_level.txt
gadfastsentry-0.0.1.dist-info/RECORD
