Metadata-Version: 2.1
Name: gadfastsentry
Version: 0.0.1
Summary: A production-ready sentry configuration module for Python.
Home-page: https://github.com/AlexDemure/gadfastsentry
Author: Alexander Grishchenko
Author-email: alexanderdemure@gmail.com
Classifier: Programming Language :: Python :: 3
Classifier: License :: OSI Approved :: MIT License
Classifier: Operating System :: OS Independent
Requires-Python: >=3.8
License-File: LICENSE
Requires-Dist: sentry-sdk
